file_watch_diagnostics/__init__.py
file_watch_diagnostics/cli/__init__.py
file_watch_diagnostics/cli/diagnostics.py
file_watch_diagnostics/cli/quick_check.py
file_watch_diagnostics/diagnostics.py
file_watch_diagnostics/utils/__init__.py
file_watch_diagnostics/utils/event_monitor.py
file_watch_diagnostics/utils/logging_utils.py
file_watch_diagnostics/utils/system_limits.py
file_watch_diagnostics/utils/watch_test.py
file_watch_diagnostics-0.1.0.dist-info/LICENSE
file_watch_diagnostics-0.1.0.dist-info/METADATA
file_watch_diagnostics-0.1.0.dist-info/WHEEL
file_watch_diagnostics-0.1.0.dist-info/entry_points.txt
file_watch_diagnostics-0.1.0.dist-info/RECORD
