Metadata-Version: 2.1
Name: file-watch-diagnostics
Version: 0.1.0
Summary: A comprehensive toolkit for diagnosing and troubleshooting file watching issues in Linux environments
Home-page: https://github.com/tom-doerr/file_watch_issue_investigation
License: MIT
Keywords: file-watching,inotify,linux,diagnostics,troubleshooting
Author: Tom Dörr
Author-email: tomdoerr96@gmail.com
Requires-Python: >=3.8.1
Classifier: Development Status :: 4 - Beta
Classifier: Environment :: Console
Classifier: Intended Audience :: Developers
Classifier: Intended Audience :: System Administrators
Classifier: License :: OSI Approved :: MIT License
Classifier: Operating System :: POSIX :: Linux
Classifier: Programming Language :: Python :: 3
Classifier: Programming Language :: Python :: 3.9
Classifier: Programming Language :: Python :: 3.10
Classifier: Programming Language :: Python :: 3.11
Classifier: Programming Language :: Python :: 3.12
Classifier: Programming Language :: Python :: 3.13
Classifier: Programming Language :: Python :: 3.8
Classifier: Topic :: System :: Monitoring
Classifier: Topic :: System :: Systems Administration
Classifier: Topic :: Utilities
Requires-Dist: psutil (>=5.9.5,<6.0.0)
Requires-Dist: pyinotify (>=0.9.6,<0.10.0)
Requires-Dist: rich (>=13.4.2,<14.0.0)
Requires-Dist: watchdog (>=3.0.0,<4.0.0)
Project-URL: Repository, https://github.com/tom-doerr/file_watch_issue_investigation
